pandas_confusion/__init__.py
pandas_confusion/stats.py
pandas_confusion/version.py
pandas_confusion-0.0.6.dist-info/DESCRIPTION.rst
pandas_confusion-0.0.6.dist-info/METADATA
pandas_confusion-0.0.6.dist-info/RECORD
pandas_confusion-0.0.6.dist-info/WHEEL
pandas_confusion-0.0.6.dist-info/entry_points.txt
pandas_confusion-0.0.6.dist-info/metadata.json
pandas_confusion-0.0.6.dist-info/pbr.json
pandas_confusion-0.0.6.dist-info/top_level.txt
