Metadata-Version: 2.0
Name: pandas-confusion
Version: 0.0.6
Summary: Pandas matrix confusion with plot features (matplotlib, seaborn...)
Home-page: https://github.com/scls19fr/pandas_confusion
Author: Sebastien Celles
Author-email: s.celles@gmail.com
License: BSD
Keywords: python pandas matrix confusion plot matplotlib seaborn machine learning
Platform: UNKNOWN
Classifier: Development Status :: 3 - Alpha
Classifier: Environment :: Console
Classifier: Intended Audience :: Developers
Classifier: Operating System :: OS Independent
Classifier: Programming Language :: Cython
Classifier: Programming Language :: Python
Classifier: Programming Language :: Python :: 2.7
Classifier: Programming Language :: Python :: 3.3
Classifier: Programming Language :: Python :: 3.4
Classifier: License :: OSI Approved :: BSD License
Requires-Dist: click
Requires-Dist: enum34
Requires-Dist: matplotlib
Requires-Dist: pandas
Requires-Dist: scikit-learn
Requires-Dist: scipy
Provides-Extra: dev
Requires-Dist: check-manifest; extra == 'dev'
Requires-Dist: nose; extra == 'dev'
Provides-Extra: test
Requires-Dist: coverage; extra == 'test'
Requires-Dist: nose; extra == 'test'
